README.md
README.rst
setup.cfg
setup.py
PP6RemoteAPI/__init__.py
PP6RemoteAPI/audio.py
PP6RemoteAPI/client.py
PP6RemoteAPI/clock.py
PP6RemoteAPI/exceptions.py
PP6RemoteAPI/library.py
PP6RemoteAPI/message.py
PP6RemoteAPI/playlist.py
PP6RemoteAPI/presentation.py
PP6RemoteAPI/stage_display.py
PP6RemoteAPI.egg-info/PKG-INFO
PP6RemoteAPI.egg-info/SOURCES.txt
PP6RemoteAPI.egg-info/dependency_links.txt
PP6RemoteAPI.egg-info/not-zip-safe
PP6RemoteAPI.egg-info/requires.txt
PP6RemoteAPI.egg-info/top_level.txt